{
	"configurations" : 
	[
		{
			"directories" : 
			[
				{
					"build" : ".",
					"hasInstallRule" : true,
					"jsonFile" : "directory-.-0d689cc5f459909e4d66.json",
					"minimumCMakeVersion" : 
					{
						"string" : "3.12"
					},
					"projectIndex" : 0,
					"source" : ".",
					"targetIndexes" : 
					[
						0,
						1,
						2
					]
				}
			],
			"name" : "",
			"projects" : 
			[
				{
					"directoryIndexes" : 
					[
						0
					],
					"name" : "motor_communication_pkg",
					"targetIndexes" : 
					[
						0,
						1,
						2
					]
				}
			],
			"targets" : 
			[
				{
					"directoryIndex" : 0,
					"id" : "motor_communication_pkg_uninstall::@6890427a1f51a3e7e1df",
					"jsonFile" : "target-motor_communication_pkg_uninstall-976886adbcf4afa48358.json",
					"name" : "motor_communication_pkg_uninstall",
					"projectIndex" : 0
				},
				{
					"directoryIndex" : 0,
					"id" : "motor_node::@6890427a1f51a3e7e1df",
					"jsonFile" : "target-motor_node-a86e28a3080e15edbbc5.json",
					"name" : "motor_node",
					"projectIndex" : 0
				},
				{
					"directoryIndex" : 0,
					"id" : "uninstall::@6890427a1f51a3e7e1df",
					"jsonFile" : "target-uninstall-221a8e1c3d4aa3143f1b.json",
					"name" : "uninstall",
					"projectIndex" : 0
				}
			]
		}
	],
	"kind" : "codemodel",
	"paths" : 
	{
		"build" : "/home/niic/427/427/sb_new_tor/WK_ZY/build/motor_communication_pkg",
		"source" : "/home/niic/427/427/sb_new_tor/WK_ZY/src/motor_communication_pkg"
	},
	"version" : 
	{
		"major" : 2,
		"minor" : 3
	}
}
